menglingtool_sqltools/__init__.py
menglingtool_sqltools/mysql.py
menglingtool_sqltools/pgsql.py
menglingtool_sqltools/sqlite.py
menglingtool_sqltools/sqlserver.py
menglingtool_sqltools/tools.py
menglingtool_sqltools/__sqltool__/action.py
menglingtool_sqltools/__sqltool__/alter.py
menglingtool_sqltools/__sqltool__/body.py
menglingtool_sqltools-1.2.2.dist-info/METADATA
menglingtool_sqltools-1.2.2.dist-info/WHEEL
menglingtool_sqltools-1.2.2.dist-info/top_level.txt
menglingtool_sqltools-1.2.2.dist-info/RECORD
