Metadata-Version: 2.1
Name: menglingtool-sqltools
Version: 1.2.2
Summary: 工业化! yyds
Home-page: https://www.python.org
Author: mengling
Author-email: 1321443305@qq.com
Requires-Python: >3.6
Requires-Dist: pyDes
